HALsn/SKU.py
HALsn/__init__.py
HALsn/dataSupervisor.py
HALsn/hardware.py
HALsn/qrCodeGen.py
HALsn/scheduler.py
HALsn/serialSupervisor.py
HALsn/socketMaster.py
HALsn/sysLogger.py
HALsn/examples/HALsn_Example.py
HALsn/examples/__init__.py
HALsn/os/__init__.py
HALsn/os/os_setup.py
HALsn/os/aws/__init__.py
HALsn/sample_data/__init__.py
HALsn/sample_data/sample_data.py
HALsn/sample_data/sf_sample.py
HALsn/sample_data/test_script.py
HALsn/sample_data/cltf_sample_csv/__init__.py
HALsn/sample_data/cltf_sample_df/BAY4.py
HALsn/sample_data/cltf_sample_df/BAY5.py
HALsn/sample_data/cltf_sample_df/BAY6.py
HALsn/sample_data/cltf_sample_df/BAY7.py
HALsn/sample_data/cltf_sample_df/__init__.py
HALsn-1.0.2.dist-info/DESCRIPTION.rst
HALsn-1.0.2.dist-info/METADATA
HALsn-1.0.2.dist-info/RECORD
HALsn-1.0.2.dist-info/WHEEL
HALsn-1.0.2.dist-info/metadata.json
HALsn-1.0.2.dist-info/top_level.txt
